tomNester.py
tomNester-1.6.0.dist-info/METADATA
tomNester-1.6.0.dist-info/WHEEL
tomNester-1.6.0.dist-info/top_level.txt
tomNester-1.6.0.dist-info/RECORD
