Metadata-Version: 2.1
Name: tomNester
Version: 1.6.0
Summary: tomNester
Home-page: https://github.com/tom/nester123
Author: tom
Author-email: m18091286648@163.com
